{
    "schema": {
        "fields": [
            {
                "name": "index",
                "type": "integer"
            },
            {
                "name": "Model Name",
                "type": "string"
            },
            {
                "name": "Model Method",
                "type": "string"
            },
            {
                "name": "Score",
                "type": "string"
            },
            {
                "name": "Difference Function",
                "type": "string"
            },
            {
                "name": "Dataframe",
                "type": "string"
            },
            {
                "name": "Duration",
                "type": "string"
            }
        ],
        "primaryKey": [
            "index"
        ],
        "pandas_version": "1.4.0"
    },
    "data": [
        {
            "index": 0,
            "Model Name": "ga_20",
            "Model Method": "genetic_algorithm",
            "Score": 0.97,
            "Difference Function": "manhattan_metrics",
            "Dataframe": "data_missing_20",
            "Duration": "187481.942 sec"
        },
        {
            "index": 1,
            "Model Name": "ga_10",
            "Model Method": "genetic_algorithm",
            "Score": 0.97,
            "Difference Function": "manhattan_metrics",
            "Dataframe": "data_missing_10",
            "Duration": "188353.460 sec"
        }
    ]
}